justembed/__init__.py
justembed/exceptions.py
justembed/core/__init__.py
justembed/core/_state.py
justembed/core/embedder.py
justembed/core/indexer.py
justembed/core/loader.py
justembed/core/logger.py
justembed/core/searcher.py
justembed/core/status.py
justembed/models/__init__.py
justembed/models/e5-small-int8.tar.gz
justembed/models/model_extractor.py
justembed/storage/__init__.py
justembed/storage/config_manager.py
justembed/storage/metadata_writer.py
justembed/storage/parquet_reader.py
justembed/storage/parquet_writer.py
justembed/utils/__init__.py
justembed/utils/hardware_detector.py
justembed/utils/limit_enforcer.py
justembed/utils/text_chunker.py
justembed/utils/timer.py
justembed/utils/validator.py
justembed-0.1.0a6.dist-info/licenses/LICENSE
justembed-0.1.0a6.dist-info/METADATA
justembed-0.1.0a6.dist-info/WHEEL
justembed-0.1.0a6.dist-info/top_level.txt
justembed-0.1.0a6.dist-info/RECORD
