Metadata-Version: 2.4
Name: justembed
Version: 0.1.0a6
Summary: A semantic engine that just works - offline-first semantic search for everyday laptops
Author-email: Krishnamoorthy Sankaran <your.email@example.com>
License: MIT
Project-URL: Homepage, https://github.com/sekarkrishna/justembed
Project-URL: Documentation, https://github.com/sekarkrishna/justembed/tree/main/docs
Project-URL: Repository, https://github.com/sekarkrishna/justembed
Project-URL: Issues, https://github.com/sekarkrishna/justembed/issues
Keywords: semantic-search,embeddings,offline,onnx,nlp,justembed
Classifier: Development Status :: 3 - Alpha
Classifier: Intended Audience :: Developers
Classifier: Intended Audience :: Science/Research
Classifier: License :: OSI Approved :: MIT License
Classifier: Programming Language :: Python :: 3
Classifier: Programming Language :: Python :: 3.8
Classifier: Programming Language :: Python :: 3.9
Classifier: Programming Language :: Python :: 3.10
Classifier: Programming Language :: Python :: 3.11
Classifier: Programming Language :: Python :: 3.12
Classifier: Topic :: Scientific/Engineering :: Artificial Intelligence
Classifier: Topic :: Text Processing :: Linguistic
Requires-Python: >=3.8
License-File: LICENSE
Requires-Dist: onnxruntime>=1.15.0
Requires-Dist: tokenizers>=0.13.0
Requires-Dist: numpy<2.0.0,>=1.20.0
Requires-Dist: polars>=0.19.0
Requires-Dist: pyarrow>=10.0.0
Requires-Dist: psutil>=5.9.0
Requires-Dist: tqdm>=4.65.0
Provides-Extra: dev
Requires-Dist: pytest>=7.4.0; extra == "dev"
Requires-Dist: pytest-cov>=4.1.0; extra == "dev"
Requires-Dist: hypothesis>=6.82.0; extra == "dev"
Requires-Dist: black>=23.7.0; extra == "dev"
Requires-Dist: ruff>=0.0.285; extra == "dev"
Requires-Dist: mypy>=1.5.0; extra == "dev"
Dynamic: license-file
